backlin/__init__.py
backlin/__main__.py
backlin/backend.py
backlin/base/DTO.py
backlin/config/env.py
backlin/config/get_redis.py
backlin/config/get_scheduler.py
backlin/crud/crud_dao.py
backlin/crud/crud_mixin.py
backlin/crud/crud_route.py
backlin/database/__init__.py
backlin/database/database.py
backlin/middleware/billing.py
backlin/middleware/log.py
backlin/module_admin/annotation/log_annotation.py
backlin/module_admin/aspect/data_scope.py
backlin/module_admin/aspect/interface_auth.py
backlin/module_admin/controller/cache_controller.py
backlin/module_admin/controller/captcha_controller.py
backlin/module_admin/controller/common_controller.py
backlin/module_admin/controller/config_controller.py
backlin/module_admin/controller/dept_controller.py
backlin/module_admin/controller/dict_controller.py
backlin/module_admin/controller/job_controller.py
backlin/module_admin/controller/log_controller.py
backlin/module_admin/controller/login_controller.py
backlin/module_admin/controller/menu_controller.py
backlin/module_admin/controller/notice_controller.py
backlin/module_admin/controller/online_controller.py
backlin/module_admin/controller/post_controler.py
backlin/module_admin/controller/role_controller.py
backlin/module_admin/controller/server_controller.py
backlin/module_admin/controller/user_controller.py
backlin/module_admin/dao/config_dao.py
backlin/module_admin/dao/dept_dao.py
backlin/module_admin/dao/dict_dao.py
backlin/module_admin/dao/job_dao.py
backlin/module_admin/dao/job_log_dao.py
backlin/module_admin/dao/log_dao.py
backlin/module_admin/dao/login_dao.py
backlin/module_admin/dao/menu_dao.py
backlin/module_admin/dao/notice_dao.py
backlin/module_admin/dao/post_dao.py
backlin/module_admin/dao/role_dao.py
backlin/module_admin/dao/user_dao.py
backlin/module_admin/entity/do/config_do.py
backlin/module_admin/entity/do/dept_do.py
backlin/module_admin/entity/do/dict_do.py
backlin/module_admin/entity/do/job_do.py
backlin/module_admin/entity/do/log_do.py
backlin-0.1.3.dist-info/METADATA
backlin-0.1.3.dist-info/WHEEL
backlin-0.1.3.dist-info/entry_points.txt
backlin-0.1.3.dist-info/RECORD
