Metadata-Version: 2.4
Name: backlin
Version: 0.1.3
Summary: SaaS backend built with FastAPI
License: MIT
Author: LinXueyuanStdio
Author-email: 23211526+LinXueyuanStdio@users.noreply.github.com
Requires-Python: >=3.11,<4.0
Classifier: License :: OSI Approved :: MIT License
Classifier: Programming Language :: Python :: 3
Classifier: Programming Language :: Python :: 3.11
Classifier: Programming Language :: Python :: 3.12
Classifier: Programming Language :: Python :: 3.13
Classifier: Programming Language :: Python :: 3.14
Requires-Dist: APScheduler
Requires-Dist: SQLAlchemy
Requires-Dist: bcrypt
Requires-Dist: contourpy
Requires-Dist: fastapi-crudrouter
Requires-Dist: fastapi[all]
Requires-Dist: gradio
Requires-Dist: ics
Requires-Dist: loguru
Requires-Dist: matplotlib
Requires-Dist: networkx
Requires-Dist: openai
Requires-Dist: openapi-schema-pydantic
Requires-Dist: openpyxl
Requires-Dist: pandas
Requires-Dist: pillow
Requires-Dist: plotly
Requires-Dist: plotly-express
Requires-Dist: psutil
Requires-Dist: psycopg2-binary (==2.9.9)
Requires-Dist: pydantic-settings
Requires-Dist: pyexcel
Requires-Dist: pyexcel-xls
Requires-Dist: pyexcel-xlsx
Requires-Dist: pyjwt
Requires-Dist: python-dotenv
Requires-Dist: python-jose
Requires-Dist: redis (==5.0.8)
Requires-Dist: requests
Requires-Dist: seaborn
Requires-Dist: sse-starlette
Requires-Dist: typer
Requires-Dist: user-agents
Requires-Dist: uvicorn
Requires-Dist: xlin
